AUTHORS.rst
LICENCE.rst
MANIFEST.in
README.rst
setup.cfg
setup.py
openpyxl/__init__.py
openpyxl/_constants.py
openpyxl/conftest.py
openpyxl/cell/__init__.py
openpyxl/cell/_writer.py
openpyxl/cell/cell.py
openpyxl/cell/read_only.py
openpyxl/cell/text.py
openpyxl/chart/_3d.py
openpyxl/chart/__init__.py
openpyxl/chart/_chart.py
openpyxl/chart/area_chart.py
openpyxl/chart/axis.py
openpyxl/chart/bar_chart.py
openpyxl/chart/bubble_chart.py
openpyxl/chart/chartspace.py
openpyxl/chart/data_source.py
openpyxl/chart/descriptors.py
openpyxl/chart/error_bar.py
openpyxl/chart/label.py
openpyxl/chart/layout.py
openpyxl/chart/legend.py
openpyxl/chart/line_chart.py
openpyxl/chart/marker.py
openpyxl/chart/picture.py
openpyxl/chart/pie_chart.py
openpyxl/chart/plotarea.py
openpyxl/chart/print_settings.py
openpyxl/chart/radar_chart.py
openpyxl/chart/reader.py
openpyxl/chart/reference.py
openpyxl/chart/scatter_chart.py
openpyxl/chart/series.py
openpyxl/chart/series_factory.py
openpyxl/chart/shapes.py
openpyxl/chart/stock_chart.py
openpyxl/chart/surface_chart.py
openpyxl/chart/text.py
openpyxl/chart/title.py
openpyxl/chart/trendline.py
openpyxl/chart/updown_bars.py
openpyxl/chartsheet/__init__.py
openpyxl/chartsheet/chartsheet.py
openpyxl/chartsheet/custom.py
openpyxl/chartsheet/properties.py
openpyxl/chartsheet/protection.py
openpyxl/chartsheet/publish.py
openpyxl/chartsheet/relation.py
openpyxl/chartsheet/views.py
openpyxl/comments/__init__.py
openpyxl/comments/author.py
openpyxl/comments/comment_sheet.py
openpyxl/comments/comments.py
openpyxl/comments/shape_writer.py
openpyxl/compat/__init__.py
openpyxl/compat/abc.py
openpyxl/compat/accumulate.py
openpyxl/compat/numbers.py
openpyxl/compat/singleton.py
openpyxl/compat/strings.py
openpyxl/descriptors/__init__.py
openpyxl/descriptors/base.py
openpyxl/descriptors/excel.py
openpyxl/descriptors/namespace.py
openpyxl/descriptors/nested.py
openpyxl/descriptors/sequence.py
openpyxl/descriptors/serialisable.py
openpyxl/descriptors/slots.py
vd42_openpyxl.egg-info/PKG-INFO
vd42_openpyxl.egg-info/SOURCES.txt
vd42_openpyxl.egg-info/dependency_links.txt
vd42_openpyxl.egg-info/requires.txt
vd42_openpyxl.egg-info/top_level.txt